dictfile/__init__.py
dictfile/api/__init__.py
dictfile/api/constants.py
dictfile/api/exceptions.py
dictfile/api/log.py
dictfile/api/parser.py
dictfile/api/patcher.py
dictfile/api/repository.py
dictfile/api/utils.py
dictfile/api/writer.py
dictfile/shell/__init__.py
dictfile/shell/causes.py
dictfile/shell/log.py
dictfile/shell/main.py
dictfile/shell/solutions.py
dictfile/shell/commands/__init__.py
dictfile/shell/commands/configure.py
dictfile/shell/commands/repository.py
dictfile-0.7.1.dist-info/METADATA
dictfile-0.7.1.dist-info/RECORD
dictfile-0.7.1.dist-info/WHEEL
dictfile-0.7.1.dist-info/entry_points.txt
dictfile-0.7.1.dist-info/top_level.txt
