Metadata-Version: 2.1
Name: dictfile
Version: 0.7.1
Summary: Command Line Interface for manipulating configuration files
Home-page: UNKNOWN
Author: Eli Polonsky
Author-email: Eli.polonsky@gmail.com
License: LICENSE
Platform: UNKNOWN
Classifier: Programming Language :: Python
Classifier: Programming Language :: Python :: 2.7
Classifier: Programming Language :: Python :: 3.6
Classifier: Natural Language :: English
Classifier: Environment :: Console
Classifier: Intended Audience :: Developers
Classifier: Intended Audience :: Information Technology
Classifier: Intended Audience :: System Administrators
Classifier: License :: OSI Approved :: Apache Software License
Classifier: Operating System :: POSIX :: Linux
Classifier: Operating System :: Microsoft
Classifier: Topic :: Software Development :: Libraries :: Python Modules
Requires-Dist: click (==6.7)
Requires-Dist: colorama (==0.3.9)
Requires-Dist: coloredlogger (==1.3.12)
Requires-Dist: flatdict (==3.0.0)
Requires-Dist: javaproperties (==0.4.0)
Requires-Dist: prettytable (==0.7.2)
Requires-Dist: PyYAML (==5.1)
Requires-Dist: six (==1.11.0)
Requires-Dist: configparser (==3.5.0)
